__init__.py
acceldata_o2a_lib-1.0.0.dist-info/licenses/LICENSE
o2a_lib/__init__.py
o2a_lib/el_fs_functions.py
o2a_lib/el_parser.py
o2a_lib/el_wf_functions.py
o2a_lib/functions.py
o2a_lib/property_utils.py
acceldata_o2a_lib-1.0.0.dist-info/METADATA
acceldata_o2a_lib-1.0.0.dist-info/WHEEL
acceldata_o2a_lib-1.0.0.dist-info/top_level.txt
acceldata_o2a_lib-1.0.0.dist-info/RECORD
