Metadata-Version: 2.4
Name: acceldata-o2a_lib
Version: 1.0.0
Summary: Additional library for Oozie To Airflow migration tool
Author-email: Sehaj Sandhu <sehaj@acceldata.io>, Jarek Potiuk <jarek.potiuk@polidea.com>, Szymon Przedwojski <szymon.przedwojski@polidea.com>, Kamil Breguła <kamil.bregula@polidea.com>, Feng Lu <fenglu@google.com>, Cameron Moberg <cjmoberg@google.com>
Project-URL: Homepage, https://github.com/GoogleCloudPlatform/oozie-to-airflow/tree/master/o2a/o2a_libs
Project-URL: Bug Tracker, https://github.com/GoogleCloudPlatform/oozie-to-airflow/issues
Classifier: Programming Language :: Python :: 3.8
Classifier: Programming Language :: Python :: 3.9
Classifier: Programming Language :: Python :: 3.10
Classifier: Programming Language :: Python :: 3.11
Classifier: License :: OSI Approved :: Apache Software License
Classifier: Operating System :: OS Independent
Requires-Python: >=3.8
License-File: LICENSE
Dynamic: license-file
